iNNsole/__init__.py
iNNsole-0.0.0.dist-info/LICENSE
iNNsole-0.0.0.dist-info/METADATA
iNNsole-0.0.0.dist-info/WHEEL
iNNsole-0.0.0.dist-info/top_level.txt
iNNsole-0.0.0.dist-info/RECORD
